dockerjudge/__init__.py
dockerjudge/dockerpy.py
dockerjudge/processor.py
dockerjudge/status.py
dockerjudge/test_case.py
dockerjudge-1.3.1.dist-info/LICENSE
dockerjudge-1.3.1.dist-info/METADATA
dockerjudge-1.3.1.dist-info/WHEEL
dockerjudge-1.3.1.dist-info/top_level.txt
dockerjudge-1.3.1.dist-info/RECORD
