Metadata-Version: 2.1
Name: dockerjudge
Version: 1.3.1
Summary: A Docker Based Online Judge Engine
Home-page: https://github.com/wxh06/dockerjudge
Author: 汪心禾
Author-email: wangxinhe06@gmail.com
License: Apache-2.0
Download-URL: https://pypi.org/simple/dockerjudge/
Project-URL: Bug Tracker, https://github.com/wxh06/dockerjudge/issues
Project-URL: Documentation, https://dockerjudge.readthedocs.io
Project-URL: Release notes, https://github.com/wxh06/dockerjudge/releases
Project-URL: Source Code, https://github.com/wxh06/dockerjudge/tree/master
Keywords: docker,online-judge,online-judge-engine
Platform: UNKNOWN
Classifier: License :: OSI Approved :: Apache Software License
Classifier: Operating System :: OS Independent
Classifier: Programming Language :: Python :: 3
Classifier: Programming Language :: Python :: 3.6
Classifier: Programming Language :: Python :: 3.7
Classifier: Programming Language :: Python :: 3.8
Classifier: Programming Language :: Python :: 3.9
Requires-Python: >=3.6
Requires-Dist: docker (>=3.7)
Provides-Extra: tls
Requires-Dist: docker[tls] (>=3.7) ; extra == 'tls'
